LICENSE
MANIFEST.in
README.txt
setup.py
atomisator/__init__.py
atomisator.indexer.egg-info/PKG-INFO
atomisator.indexer.egg-info/SOURCES.txt
atomisator.indexer.egg-info/dependency_links.txt
atomisator.indexer.egg-info/entry_points.txt
atomisator.indexer.egg-info/namespace_packages.txt
atomisator.indexer.egg-info/not-zip-safe
atomisator.indexer.egg-info/requires.txt
atomisator.indexer.egg-info/top_level.txt
atomisator/indexer/__init__.py
atomisator/indexer/tests/__init__.py
atomisator/indexer/tests/test_indexer.py