Metadata-Version: 1.0
Name: atomisator.indexer
Version: 0.1.0
Summary: Atomisator - Indexing
Home-page: http://atomisator.ziade.org
Author: Tarek Ziade
Author-email: tarek@ziade.org
License: Python
Keywords: atomisator indexer xapian
Platform: UNKNOWN
Classifier: Programming Language :: Python
Classifier: Topic :: Software Development :: Libraries :: Python Modules
Classifier: License :: OSI Approved :: Python Software Foundation License
